fern/__init__.py
fern/client.py
fern/core/__init__.py
fern/core/api_error.py
fern/core/client_wrapper.py
fern/core/datetime_utils.py
fern/core/jsonable_encoder.py
fern/core/remove_none_from_dict.py
fern/environment.py
fern/py.typed
fern/resources/__init__.py
fern/resources/snippets/__init__.py
fern/resources/snippets/client.py
fern/resources/snippets/errors/__init__.py
fern/resources/snippets/errors/api_id_not_found.py
fern/resources/snippets/errors/api_id_required_error.py
fern/resources/snippets/errors/endpoint_not_found.py
fern/resources/snippets/errors/invalid_page_error.py
fern/resources/snippets/errors/org_id_and_api_id_not_found.py
fern/resources/snippets/errors/org_id_not_found.py
fern/resources/snippets/errors/org_id_required_error.py
fern/resources/snippets/errors/sdk_not_found.py
fern/resources/snippets/resources/__init__.py
fern/resources/snippets/resources/commons/__init__.py
fern/resources/snippets/resources/commons/errors/__init__.py
fern/resources/snippets/resources/commons/errors/unauthorized_error.py
fern/resources/snippets/resources/commons/errors/unavailable_error.py
fern/resources/snippets/resources/commons/errors/user_not_in_org_error.py
fern/resources/snippets/resources/commons/types/__init__.py
fern/resources/snippets/resources/commons/types/api_id.py
fern/resources/snippets/resources/commons/types/org_id.py
fern/resources/snippets/types/__init__.py
fern/resources/snippets/types/endpoint_identifier.py
fern/resources/snippets/types/endpoint_method.py
fern/resources/snippets/types/endpoint_path.py
fern/resources/snippets/types/go_sdk.py
fern/resources/snippets/types/go_snippet.py
fern/resources/snippets/types/java_sdk.py
fern/resources/snippets/types/java_snippet.py
fern/resources/snippets/types/python_sdk.py
fern/resources/snippets/types/python_snippet.py
fern/resources/snippets/types/sdk.py
fern/resources/snippets/types/snippet.py
fern/resources/snippets/types/snippets_by_endpoint_method.py
fern/resources/snippets/types/snippets_page.py
fern_api-0.1.1.dist-info/METADATA
fern_api-0.1.1.dist-info/WHEEL
fern_api-0.1.1.dist-info/RECORD
